{
  "price_criteria_key": "req_parts_772",
  "source": "SERVICE_ADVISOR_TERMINAL",
  "locale": {
    "locale_name": "US_GA_ATLANTA",
    "currency_code": "USD",
    "location_code": "SERVICE_BAY_04"
  },
  "price_min": {
    "value": "40.00",
    "currency_code": "USD"
  },
  "price_max": {
    "value": "150.00",
    "currency_code": "USD"
  },
  "price_criteria_items": [
    {
      "price_criteria_item_key": "item_brakes_001",
      "part_identifier": [
        {
          "part_identifier_type": "NAME",
          "part_identifier_value": "Ceramic Brake Pad Set",
          "description": "Front Axle Ceramic Brakes"
        },
        {
          "part_identifier_type": "SKU",
          "part_identifier_value": "BP-9988-CER"
        }
      ],
      "party_types": ["SERVICE"],
      "payment_types": ["OUTRIGHT_PURCHASE"]
    }
  ]
}