{
  "product_contract_id": "550e8400-e29b-41d4-a716-446655440000",
  "product_contract_key": "CONT-TFS-GAP-2026",
  "contract_number": "0060003675",
  "execution_date": "2026-01-16T00:00:00Z",
  "expiration_date": "2029-01-15T00:00:00Z",
  "effective_period": {
    "start_date_time": "2026-01-16T00:00:00Z",
    "complete_date_time": "2029-01-15T00:00:00Z"
  },
  "expiration_distance": 100000,
  "term_units": "MONTHS",
  "term_value": "36",
  "capitalization_indicator": true,
  "financed_indicator": true,
  "taxability_indicator": false,
  "contract_types": ["PROTECTION"],
  "price_summary": {
    "price_summary_id": "PS-GAP-01",
    "prices": [
      {
        "price_id": "PRC-PREMIUM",
        "value": "1200.00",
        "currency_code": "USD",
        "price_types": ["PREMIUM_TOTAL"]
      },
      {
        "price_id": "PRC-DISABILITY",
        "value": "50.00",
        "currency_code": "USD",
        "price_types": ["DISABILITY_PREMIUM_TOTAL"]
      }
    ]
  },
  "identifiers": [
    {
      "identifier_id": "VIN-5TFHY5F13KX799310",
      "identifier_type": "VIN",
      "value": "5TFHY5F13KX799310"
    },
    {
      "identifier_id": "SUB-PLATINUM",
      "identifier_type": "SUBTYPE",
      "value": "PLATINUM"
    }
  ],
  "party_references": [
    {
      "party_reference_id": "PR-04-DEALER",
      "party_relationship_types": ["PROVIDER", "SERVICE_PROVIDER"],
      "source_system_code": "PRO-ATL-05",
      "party": {
        "identifier_id": "PTY-673876",
        "value": "Service A. Provider",
        "identifier_type": "ORGANIZATION_ID"
      }
    }
  ]
}