{
  "features": [
    {
      "feature_id": "feat_001",
      "feature_key": "interior_dims",
      "header": "Interior dimensions, front/rear (in.)",
      "description": "EFC Other than Std Feature Details",
      "feature_details": [
        {
          "feature_item_id": "det_001",
          "feature_item_key": "mechanical_spec",
          "detail_name": "Engine/Transmission",
          "detail_value": "3.5L V6 DOHC 24-Valve D-4S Injection with Dual VVT-i -Direct Shift 8-Speed Automatic Transmission"
        },
        {
          "feature_item_id": "det_002",
          "feature_item_key": "wheel_spec",
          "detail_name": "Wheels/Tires",
          "detail_value": "18-in. Alloy Wheels with P235/55RF18 Tires -Active Torque Control AWD System"
        }
      ]
    }
  ],
  "options": [
    {
      "option_id": "std_opt_001",
      "option_key": "safety_convenience",
      "option_name": "Safety and Convenience",
      "short_description": "Standard Options",
      "option_descriptions": [
        {
          "option_description_id": "od_001",
          "description": "Child-protector rear door locks",
          "group_name": "SAFETY"
        },
        {
          "option_description_id": "od_002",
          "description": "Tire Pressure Monitor System (TPMS)",
          "group_name": "SAFETY"
        }
      ]
    },
    {
      "option_id": "std_opt_002",
      "option_key": "mechanical_performance",
      "option_name": "Mechanical and Performance",
      "option_descriptions": [
        {
          "option_description_id": "od_003",
          "description": "Steering: Hydraulic power rack-and-pinion",
          "group_name": "MECHANICAL"
        }
      ]
    }
  ]
}